operate_tools/__init__.py
operate_tools/_date.py
operate_tools/_file.py
operate_tools-1.0.6.dist-info/LICENSE
operate_tools-1.0.6.dist-info/METADATA
operate_tools-1.0.6.dist-info/WHEEL
operate_tools-1.0.6.dist-info/top_level.txt
operate_tools-1.0.6.dist-info/RECORD
