Metadata-Version: 2.1
Name: operate-tools
Version: 1.0.6
Summary: Python操作工具合集
Home-page: https://github.com/Joker-desire/operate-tools
Author: Joker-desire
Author-email: 2590205729@qq.com
License: MIT Licence
Platform: any
Requires: chardet
License-File: LICENSE
